valapi/__init__.py
valapi/auth.py
valapi/client.py
valapi/exceptions.py
valapi/resources.py
valapi-1.13.dist-info/METADATA
valapi-1.13.dist-info/WHEEL
valapi-1.13.dist-info/top_level.txt
valapi-1.13.dist-info/RECORD
